jwtberry/__init__.py
jwtberry/apps.py
jwtberry/auth.py
jwtberry/backends.py
jwtberry/blackberry/__init__.py
jwtberry/blackberry/admin.py
jwtberry/blackberry/apps.py
jwtberry/blackberry/migrations/0001_initial.py
jwtberry/blackberry/migrations/__init__.py
jwtberry/blackberry/models.py
jwtberry/context.py
jwtberry/core.py
jwtberry/exceptions.py
jwtberry/helper.py
jwtberry/models.py
jwtberry/mutations.py
jwtberry/permission.py
jwtberry/settings.py
jwtberry/tests.py
jwtberry/tokens.py
jwtberry/types.py
jwtberry/views.py
jwtberry-0.1.0.dist-info/METADATA
jwtberry-0.1.0.dist-info/WHEEL
jwtberry-0.1.0.dist-info/RECORD
