Metadata-Version: 2.1
Name: jwtberry
Version: 0.1.0
Summary: 
Author: Vachagan
Author-email: vachagan.grigoryan@outlook.com
Requires-Python: >=3.11,<4.0
Classifier: Programming Language :: Python :: 3
Classifier: Programming Language :: Python :: 3.11
Requires-Dist: django (>=4.2.6,<5.0.0)
Requires-Dist: pyjwt (>=2.8.0,<3.0.0)
Requires-Dist: strawberry-graphql (>=0.211.1,<0.212.0)
